mobilitydb_sqlalchemy/__init__.py
mobilitydb_sqlalchemy/comparator.py
mobilitydb_sqlalchemy/types/TBaseGeomPoint.py
mobilitydb_sqlalchemy/types/TBaseType.py
mobilitydb_sqlalchemy/types/TBool.py
mobilitydb_sqlalchemy/types/TFloat.py
mobilitydb_sqlalchemy/types/TGeogPoint.py
mobilitydb_sqlalchemy/types/TGeomPoint.py
mobilitydb_sqlalchemy/types/TInt.py
mobilitydb_sqlalchemy/types/__init__.py
mobilitydb_sqlalchemy/utils.py
mobilitydb_sqlalchemy-0.3.dist-info/LICENSE.txt
mobilitydb_sqlalchemy-0.3.dist-info/WHEEL
mobilitydb_sqlalchemy-0.3.dist-info/METADATA
mobilitydb_sqlalchemy-0.3.dist-info/RECORD
