Metadata-Version: 2.1
Name: mobilitydb-sqlalchemy
Version: 0.3
Summary: MobilityDB extensions to SQLAlchemy
Home-page: https://github.com/adonmo/mobilitydb-sqlalchemy
License: MIT
Keywords: geo,gis,postgres,mobilitydb,sqlalchemy,orm
Author: B Krishna Chaitanya
Author-email: bkchaitan94@gmail.com
Requires-Python: >=3.7
Classifier: Development Status :: 3 - Alpha
Classifier: Environment :: Plugins
Classifier: Intended Audience :: Developers
Classifier: Intended Audience :: Information Technology
Classifier: Intended Audience :: Science/Research
Classifier: License :: OSI Approved :: MIT License
Classifier: Natural Language :: English
Classifier: Operating System :: OS Independent
Classifier: Programming Language :: Python
Classifier: Programming Language :: Python :: 3
Classifier: Programming Language :: Python :: 3.7
Classifier: Programming Language :: Python :: 3.8
Classifier: Topic :: Database :: Database Engines/Servers
Classifier: Topic :: Scientific/Engineering :: GIS
Provides-Extra: docs
Provides-Extra: movingpandas
Requires-Dist: geoalchemy2 (>=0.8.4,<0.9.0)
Requires-Dist: movingpandas (>=0.4rc1,<0.5); extra == "movingpandas"
Requires-Dist: pandas (>=1.1.0,<2.0.0)
Requires-Dist: pymeos (>=0.1,<0.2)
Requires-Dist: shapely (>=1.7.0,<2.0.0)
Requires-Dist: sphinx (>=2.3.1,<3.0.0); extra == "docs"
Requires-Dist: sphinx-rtd-theme (>=0.4.3,<0.5.0); extra == "docs"
Requires-Dist: sqlalchemy (>=1.3.18,<2.0.0)
Requires-Dist: tomlkit (>=0.5.8,<0.6.0); extra == "docs"
Project-URL: Documentation, https://mobilitydb-sqlalchemy.readthedocs.io/en/latest/
Project-URL: Repository, https://github.com/adonmo/mobilitydb-sqlalchemy
